odoo/addons/report_qweb_pdf_cover/README.rst
odoo/addons/report_qweb_pdf_cover/__init__.py
odoo/addons/report_qweb_pdf_cover/__manifest__.py
odoo/addons/report_qweb_pdf_cover/i18n/es.po
odoo/addons/report_qweb_pdf_cover/i18n/it.po
odoo/addons/report_qweb_pdf_cover/i18n/report_qweb_pdf_cover.pot
odoo/addons/report_qweb_pdf_cover/models/__init__.py
odoo/addons/report_qweb_pdf_cover/models/ir_actions_report.py
odoo/addons/report_qweb_pdf_cover/readme/CONTRIBUTORS.md
odoo/addons/report_qweb_pdf_cover/readme/DESCRIPTION.md
odoo/addons/report_qweb_pdf_cover/readme/USAGE.md
odoo/addons/report_qweb_pdf_cover/static/description/icon.png
odoo/addons/report_qweb_pdf_cover/static/description/index.html
odoo/addons/report_qweb_pdf_cover/views/ir_actions_views.xml
odoo_addon_report_qweb_pdf_cover-18.0.1.0.0.4.dist-info/METADATA
odoo_addon_report_qweb_pdf_cover-18.0.1.0.0.4.dist-info/WHEEL
odoo_addon_report_qweb_pdf_cover-18.0.1.0.0.4.dist-info/top_level.txt
odoo_addon_report_qweb_pdf_cover-18.0.1.0.0.4.dist-info/RECORD
